phdl_py/__init__.py
phdl_py/configLog.yaml
phdl_py/configlogger.py
phdl_py/main.py
phdl_py/utils.py
phdl_py-0.0.2.dist-info/entry_points.txt
phdl_py-0.0.2.dist-info/LICENSE
phdl_py-0.0.2.dist-info/WHEEL
phdl_py-0.0.2.dist-info/METADATA
phdl_py-0.0.2.dist-info/RECORD
